experimental/__init__.py
experimental/ty/__init__.py
experimental/ty/register.py
experimental/ty/rules.py
experimental/ty/skip_field.py
experimental/ty/subsystems.py
robotpajamas_pants_ty-0.0.1.dist-info/METADATA
robotpajamas_pants_ty-0.0.1.dist-info/WHEEL
robotpajamas_pants_ty-0.0.1.dist-info/namespace_packages.txt
robotpajamas_pants_ty-0.0.1.dist-info/top_level.txt
robotpajamas_pants_ty-0.0.1.dist-info/RECORD
