Metadata-Version: 2.4
Name: robotpajamas.pants.ty
Version: 0.0.1
Summary: A Pants plugin adding support for the Ty type checker.
License: Apache License, Version 2.0
Project-URL: Documentation, https://github.com/sureshjoshi/pants-plugins
Project-URL: Source, https://github.com/sureshjoshi/pants-plugins
Project-URL: Tracker, https://github.com/sureshjoshi/pants-plugins/issues
Project-URL: Changelog, https://github.com/sureshjoshi/pants-plugins/blob/main/pants-plugins/experimental/ty/CHANGELOG.md
Keywords: pants,pants-plugin,ty
Classifier: Intended Audience :: Developers
Classifier: License :: OSI Approved :: Apache Software License
Classifier: Operating System :: MacOS :: MacOS X
Classifier: Operating System :: POSIX :: Linux
Classifier: Programming Language :: Python
Classifier: Programming Language :: Python :: 3 :: Only
Classifier: Topic :: Software Development :: Build Tools
Requires-Python: >=3.11.0
Dynamic: classifier
Dynamic: description
Dynamic: description-content-type
Dynamic: keywords
Dynamic: license
Dynamic: project-url
Dynamic: requires-python
Dynamic: summary
